nazoru/__init__.py
nazoru/bluetooth.py
nazoru/core.py
nazoru/keyboard_recorder.py
nazoru/led.py
nazoru/lib.py
nazoru/nazoru_test.py
nazoru/nazorunet.py
nazoru/predictor.py
nazoru/utils.py
nazoru/data/optimized_nazoru.pb
nazoru_input-0.1.2.data/scripts/nazoru-input
nazoru_input-0.1.2.data/scripts/nazoru-training
nazoru_input-0.1.2.dist-info/METADATA
nazoru_input-0.1.2.dist-info/WHEEL
nazoru_input-0.1.2.dist-info/top_level.txt
nazoru_input-0.1.2.dist-info/RECORD
