Metadata-Version: 2.1
Name: nazoru-input
Version: 0.1.2
Summary: Package for Gboard Physical Handwriting Version
Home-page: https://landing.google.com/tegaki
Author: Makoto Shimazu
Author-email: shimazu@google.com
License: Apache
Classifier: Development Status :: 3 - Alpha
Classifier: Environment :: Console
Classifier: Environment :: No Input/Output (Daemon)
Classifier: Operating System :: OS Independent
Classifier: Programming Language :: Python
Classifier: License :: OSI Approved :: Apache Software License
Classifier: Topic :: Scientific/Engineering :: Artificial Intelligence
Classifier: Topic :: Software Development :: Libraries :: Python Modules
Classifier: Topic :: Utilities
Requires-Python: >=3.8, <3.12
Requires-Dist: cairocffi
Requires-Dist: pillow
Requires-Dist: tensorflow ~=2.12.1
Requires-Dist: tf-slim ~=1.1.0
Requires-Dist: pyserial
Requires-Dist: evdev ; platform_system == "Linux"
Requires-Dist: wiringpi ; platform_system == "Linux"
Requires-Dist: enum34 ; python_version < "3.4"
